bombaat/__init__.py
bombaat/__main__.py
bombaat/argparser.py
bombaat/configure.py
bombaat/downloader.py
bombaat/driver.py
bombaat/errors.py
bombaat/init.py
bombaat/login.py
bombaat/profiles.py
bombaat/saml.py
bombaat/utils.py
bombaat-1.1.1.dist-info/LICENSE
bombaat-1.1.1.dist-info/METADATA
bombaat-1.1.1.dist-info/WHEEL
bombaat-1.1.1.dist-info/entry_points.txt
bombaat-1.1.1.dist-info/top_level.txt
bombaat-1.1.1.dist-info/RECORD
