Metadata-Version: 2.1
Name: bombaat
Version: 1.1.1
Summary: Bombaat CLI - awscli / boto AWS API access using Azure Active Directory (AD) service.
Home-page: UNKNOWN
Author: Ravi Boodher
Author-email: boodher@gmail.com
License: UNKNOWN
Platform: UNKNOWN
Classifier: Programming Language :: Python :: 3
Classifier: Topic :: Utilities
Classifier: Environment :: Console
Classifier: Operating System :: POSIX
Classifier: Operating System :: MacOS
Classifier: Operating System :: Unix
Requires-Python: >=3.6
Requires-Dist: boto (==2.49.0)
Requires-Dist: tqdm (==4.50.2)
Requires-Dist: PyYAML (==5.3.1)
Requires-Dist: boto3 (==1.16.43)
Requires-Dist: appdirs (==1.4.4)
Requires-Dist: urllib3 (==1.25.8)
Requires-Dist: inquirer (==2.7.0)
Requires-Dist: colorlog (==4.6.2)
Requires-Dist: blessed (==1.17.6)
Requires-Dist: awscli (==1.18.205)
Requires-Dist: selenium (==3.141.0)
Requires-Dist: botocore (==1.19.45)
